{
  "en": {
    "title": "SU Sanam Chan Bathroom Map",
    "navTitle": "SU Sanam Chan Bathroom Map",
    "navTitleShort": "SU Sanam Chan WC Map",
    "satellite": "Satellite",
    "darkMode": "Dark Mode",
    "searchPlaceholder": "Search restrooms...",
    "open": "Open:",
    "legend": "Legend",
    "statusOpen": "Open",
    "statusClosed": "Closed",
    "statusStaff": "Staff Only",
    "statusStudent": "Students Only",
    "statusAll": "All (Staff & Students)",
    "accessLabel": "Access:",
    "noteLabel": "Note:",
    "placesListTitle": "Restroom Directory",
    "sortAZ": "A-Z",
    "sortNearest": "Nearest",
    "filterTitle": "Filter Restrooms",
    "filterAny": "Any",
    "filterAll": "All",
    "filterStudents": "Students",
    "filterStaff": "Staff",
    "filterSpecific": "Specific Hours",
    "filter24h": "24 Hours",
    "applyFilter": "Apply Filter",
    "addPlaceTitle": "Add New Place",
    "addPlaceSubtitle": "Submit a place for admin review.",
    "modalPrimaryName": "Place Name (English) *Primary",
    "modalTranslations": "🌍 Add Translations",
    "modalOpHours": "Operating Hours",
    "modalAccess": "Access",
    "modalNote": "Note (Optional)",
    "modalLocation": "Attachments & Location",
    "pickLocation": "📍 Pick Map Location",
    "btnCancel": "Cancel",
    "btnSubmit": "Submit Place",
    "mapConfirmText": "Drag the map to the exact location.",
    "btnConfirm": "Confirm"
  },
  "th": {
    "title": "แผนที่ห้องน้ำ ม.ศิลปากร (สนามจันทร์)",
    "navTitle": "แผนที่ห้องน้ำ ม.ศิลปากร (สนามจันทร์)",
    "navTitleShort": "แผนที่ห้องน้ำ ม.ศิลปากร (สนามจันทร์)",
    "satellite": "ดาวเทียม",
    "darkMode": "โหมดมืด",
    "searchPlaceholder": "ค้นหาห้องน้ำ...",
    "open": "เปิด:",
    "legend": "สัญลักษณ์",
    "statusOpen": "เปิด",
    "statusClosed": "ปิด",
    "statusStaff": "เฉพาะบุคลากร",
    "statusStudent": "เฉพาะนักศึกษา",
    "statusAll": "ทุกคน (บุคลากรและนักศึกษา)",
    "accessLabel": "สิทธิ์การเข้าถึง:",
    "noteLabel": "หมายเหตุ:",
    "placesListTitle": "รายชื่อห้องน้ำ",
    "sortAZ": "ก-ฮ",
    "sortNearest": "ใกล้ที่สุด",
    "filterTitle": "กรองห้องน้ำ",
    "filterAny": "ใดก็ได้",
    "filterAll": "ทุกคน",
    "filterStudents": "นักศึกษา",
    "filterStaff": "บุคลากร",
    "filterSpecific": "เวลาเฉพาะ",
    "filter24h": "24 ชั่วโมง",
    "applyFilter": "ตกลง",
    "addPlaceTitle": "เพิ่มสถานที่ใหม่",
    "addPlaceSubtitle": "ส่งสถานที่เพื่อให้ผู้ดูแลระบบตรวจสอบ",
    "modalPrimaryName": "ชื่อสถานที่ (ภาษาอังกฤษ) *หลัก",
    "modalTranslations": "🌍 เพิ่มคำแปล",
    "modalOpHours": "เวลาเปิดทำการ",
    "modalAccess": "สิทธิ์การเข้าถึง",
    "modalNote": "หมายเหตุ (ไม่บังคับ)",
    "modalLocation": "รูปภาพและตำแหน่ง",
    "pickLocation": "📍 เลือกตำแหน่งบนแผนที่",
    "btnCancel": "ยกเลิก",
    "btnSubmit": "ส่งสถานที่",
    "mapConfirmText": "ลากแผนที่ไปยังตำแหน่งที่ถูกต้อง",
    "btnConfirm": "ยืนยัน"
  },
  "cn": {
    "title": "SU Sanam Chan 洗手间地图",
    "navTitle": "SU Sanam Chan 洗手间地图",
    "navTitleShort": "SU Sanam Chan WC 地图",
    "satellite": "卫星图",
    "darkMode": "深色模式",
    "searchPlaceholder": "搜索洗手间...",
    "open": "营业:",
    "legend": "图例",
    "statusOpen": "营业中",
    "statusClosed": "已关闭",
    "statusStaff": "仅限员工",
    "statusStudent": "仅限学生",
    "statusAll": "所有人 (教职员工和学生)",
    "accessLabel": "访问权限:",
    "noteLabel": "注意:",
    "placesListTitle": "洗手间目录",
    "sortAZ": "A-Z",
    "sortNearest": "最近",
    "filterTitle": "筛选洗手间",
    "filterAny": "任何",
    "filterAll": "所有人",
    "filterStudents": "学生",
    "filterStaff": "员工",
    "filterSpecific": "特定时间",
    "filter24h": "24小时",
    "applyFilter": "应用筛选",
    "addPlaceTitle": "添加新地点",
    "addPlaceSubtitle": "提交地点供管理员审核。",
    "modalPrimaryName": "地点名称 (英文) *主要",
    "modalTranslations": "🌍 添加翻译",
    "modalOpHours": "营业时间",
    "modalAccess": "访问权限",
    "modalNote": "注意 (可选)",
    "modalLocation": "附件和位置",
    "pickLocation": "📍 在地图上选择位置",
    "btnCancel": "取消",
    "btnSubmit": "提交地点",
    "mapConfirmText": "将地图拖到准确位置。",
    "btnConfirm": "确认"
  },
  "kh": {
    "title": "ផែនទីបន្ទប់ទឹក SU (Sanam Chan)",
    "navTitle": "ផែនទីបន្ទប់ទឹក SU (Sanam Chan)",
    "navTitleShort": "ផែនទី WC SU (Sanam Chan)",
    "satellite": "ផ្កាយរណប",
    "darkMode": "ម៉ូតងងឹត",
    "searchPlaceholder": "ស្វែងរកបន្ទប់ទឹក...",
    "open": "បើក៖",
    "legend": "កំណត់ចំណាំ",
    "statusOpen": "បើក",
    "statusClosed": "បិទ",
    "statusStaff": "សម្រាប់តែបុគ្គលិក",
    "statusStudent": "សម្រាប់តែសិស្ស",
    "statusAll": "ទាំងអស់ (បុគ្គលិក និងសិស្ស)",
    "accessLabel": "សិទ្ធិចូលប្រើ:",
    "noteLabel": "ចំណាំ៖",
    "placesListTitle": "បញ្ជីបន្ទប់ទឹក",
    "sortAZ": "A-Z",
    "sortNearest": "ជិតបំផុត",
    "filterTitle": "ចម្រោះបន្ទប់ទឹក",
    "filterAny": "ណាមួយ",
    "filterAll": "ទាំងអស់",
    "filterStudents": "សិស្ស",
    "filterStaff": "បុគ្គលិក",
    "filterSpecific": "ម៉ោងជាក់លាក់",
    "filter24h": "24 ម៉ោង",
    "applyFilter": "អនុវត្ត",
    "addPlaceTitle": "បន្ថែមទីតាំងថ្មី",
    "addPlaceSubtitle": "ដាក់ស្នើទីតាំងសម្រាប់ការពិនិត្យ។",
    "modalPrimaryName": "ឈ្មោះទីតាំង (អង់គ្លេស) *ចម្បង",
    "modalTranslations": "🌍 បន្ថែមការបកប្រែ",
    "modalOpHours": "ម៉ោងប្រតិបត្តិការ",
    "modalAccess": "សិទ្ធិចូលប្រើ",
    "modalNote": "ចំណាំ (ស្រេចចិត្ត)",
    "modalLocation": "ឯកសារភ្ជាប់និងទីតាំង",
    "pickLocation": "📍 ជ្រើសរើសទីតាំងផែនទី",
    "btnCancel": "បោះបង់",
    "btnSubmit": "ដាក់ស្នើទីតាំង",
    "mapConfirmText": "អូសផែនទីទៅទីតាំងពិតប្រាកដ។",
    "btnConfirm": "បញ្ជាក់"
  }
}